MANIFEST.in
setup.py
shelf_loader/__init__.py
shelf_loader/__main__.py
shelf_loader/consts.py
shelf_loader/loader.py
shelf_loader.egg-info/PKG-INFO
shelf_loader.egg-info/SOURCES.txt
shelf_loader.egg-info/dependency_links.txt
shelf_loader.egg-info/requires.txt
shelf_loader.egg-info/top_level.txt
shelf_loader/extractors/__init__.py
shelf_loader/extractors/base_extractor.py
shelf_loader/extractors/loader_information_extractor.py
shelf_loader/extractors/opcodes.py
shelf_loader/extractors/utils.py
shelf_loader/interactive_debugger/__init__.py
shelf_loader/interactive_debugger/interactive_debugger.py
shelf_loader/interactive_debugger/gdb_scripts/__init__.py
shelf_loader/interactive_debugger/gdb_scripts/gdb_main.py
shelf_loader/interactive_debugger/gdb_scripts/shelf_debug_flow.py
shelf_loader/resources/__init__.py
shelf_loader/resources/shellcode_loader_.out
shelf_loader/resources/shellcode_loader_aarch64.out
shelf_loader/resources/shellcode_loader_arm32.out
shelf_loader/resources/shellcode_loader_intel_x32.out
shelf_loader/resources/shellcode_loader_intel_x64.out
shelf_loader/resources/shellcode_loader_mips.out
shelf_loader/resources/shellcode_loader_no_rwx_.out
shelf_loader/resources/shellcode_loader_no_rwx_aarch64.out
shelf_loader/resources/shellcode_loader_no_rwx_arm32.out
shelf_loader/resources/shellcode_loader_no_rwx_intel_x32.out
shelf_loader/resources/shellcode_loader_no_rwx_intel_x64.out
shelf_loader/resources/shellcode_loader_no_rwx_mips.out
shelf_loader/resources/shellcode_loader_no_rwx_riscv64.out
shelf_loader/resources/shellcode_loader_riscv64.out