Metadata-Version: 2.1
Name: shelf-loader
Version: 1.0.0
Summary: The loader of the py_shelf package
Home-page: https://github.com/jonatanSh/shelf
Author: Jonathan Shimon
Author-email: jonatanshimon@gmail.com
License: MIT License
Platform: UNKNOWN
